sova/__init__.py
sova/backend/__init__.py
sova/backend/backend.py
sova/backend/bareg.py
sova/backend/eigen_factor.py
sova/backend/mrob_backend.py
sova/filter/__init__.py
sova/filter/empty_voxel.py
sova/filter/filter.py
sova/pipeline/__init__.py
sova/pipeline/configuration/__init__.py
sova/pipeline/configuration/reader.py
sova/pipeline/configuration/yaml.py
sova/pipeline/pipeline.py
sova/pipeline/sequential_pipeline.py
sova/segmenter/__init__.py
sova/segmenter/cape.py
sova/segmenter/count.py
sova/segmenter/identical.py
sova/segmenter/ransac.py
sova/segmenter/segmenter.py
sova/subdivider/__init__.py
sova/subdivider/count.py
sova/subdivider/eigen_value.py
sova/subdivider/size.py
sova/subdivider/subdivider.py
sova/typing/__init__.py
sova/typing/hints.py
sova/utils/__init__.py
sova/utils/dataset_reader/__init__.py
sova/utils/dataset_reader/hilti.py
sova/utils/dataset_reader/kitti.py
sova/utils/dataset_reader/nuscenes.py
sova/utils/dataset_reader/reader.py
sova/utils/pose_readwriter.py
sova-0.1.0.dist-info/LICENSE
sova-0.1.0.dist-info/METADATA
sova-0.1.0.dist-info/WHEEL
sova-0.1.0.dist-info/RECORD
