Metadata-Version: 2.1
Name: sova
Version: 0.1.0
Summary: SLAM on Voxel Alignment
Home-page: https://github.com/prime-slam/
License: APACHE
Author: Pavel Mokeev
Author-email: pav3l.mokeev@gmail.com
Requires-Python: ==3.10.*
Classifier: Intended Audience :: Developers
Classifier: License :: OSI Approved :: Apache Software License
Classifier: License :: Other/Proprietary License
Classifier: Programming Language :: Python :: 3
Classifier: Programming Language :: Python :: 3.10
Classifier: Topic :: Software Development :: Libraries :: Python Modules
Requires-Dist: PyYAML (>=6.0.1,<6.1.0)
Requires-Dist: mrob (>=0.0.12,<0.0.13)
Requires-Dist: numpy (>=1.26.0,<2.0.0)
Requires-Dist: octreelib (>=0.0.6,<0.0.7)
Requires-Dist: open3d (>=0.17.0,<0.18.0)
Requires-Dist: scikit-learn (>=1.3.1,<2.0.0)
Project-URL: Repository, https://github.com/prime-slam/sova
